datadiode_RobustSoliton/RobustSolitonReceiver.py
datadiode_RobustSoliton/RobustSolitonSender.py
datadiode_RobustSoliton/__init__.py
datadiode_RobustSoliton/__main__.py
datadiode_RobustSoliton/fastfe.py
datadiode_RobustSoliton/fixed_fec.py
datadiode_RobustSoliton/prng.py
datadiode_RobustSoliton/soliton.py
datadiode_RobustSoliton/utils.py
datadiode_robustsoliton-1.0.0.dist-info/licenses/LICENSE
datadiode_robustsoliton-1.0.0.dist-info/METADATA
datadiode_robustsoliton-1.0.0.dist-info/WHEEL
datadiode_robustsoliton-1.0.0.dist-info/entry_points.txt
datadiode_robustsoliton-1.0.0.dist-info/top_level.txt
datadiode_robustsoliton-1.0.0.dist-info/RECORD
