Metadata-Version: 2.4
Name: datadiode-RobustSoliton
Version: 1.0.0
Summary: Reliable one-way file transfer using Robust Soliton fountain codes
Home-page: https://github.com/BANPUMP-team/datadiode-RobustSoliton
Author: Alin-Adrian Anton
Author-email: alin.anton@upt.ro
Classifier: Programming Language :: Python :: 3
Classifier: License :: OSI Approved :: GNU General Public License v3 (GPLv3)
Classifier: Operating System :: OS Independent
Classifier: Topic :: System :: Networking
Classifier: Topic :: Communications :: File Sharing
Requires-Python: >=3.6
License-File: LICENSE
Requires-Dist: numpy>=1.20.0
Requires-Dist: tqdm>=4.62.0
Dynamic: author
Dynamic: author-email
Dynamic: classifier
Dynamic: description
Dynamic: description-content-type
Dynamic: home-page
Dynamic: license-file
Dynamic: requires-dist
Dynamic: requires-python
Dynamic: summary
